csp_bot_commands/__init__.py
csp_bot_commands/common.py
csp_bot_commands/delaytest.py
csp_bot_commands/fun.py
csp_bot_commands/mets.py
csp_bot_commands/thanks.py
csp_bot_commands/trout.py
csp_bot_commands/tests/test_all.py
csp_bot_commands/tests/test_fun.py
csp_bot_commands/tests/test_mets.py
csp_bot_commands/tests/test_thanks.py
csp_bot_commands/tests/test_trout.py
csp_bot_commands-1.0.0.dist-info/METADATA
csp_bot_commands-1.0.0.dist-info/WHEEL
csp_bot_commands-1.0.0.dist-info/licenses/LICENSE
csp_bot_commands-1.0.0.dist-info/RECORD
